{
    "moves": {
        "normal": {
            "Stand LP": {
                "moveName": "Stand LP",
                "plnCmd": "LP",
                "numCmd": "5LP",
                "startup": 4,
                "active": 6,
                "recovery": 6,
                "onBlock": 2,
                "onHit": 2,
                "onHitCrouch": 2,
                "moveType": "normal",
                "cancelsTo": [
                    "self",
                    "sp",
                    "su"
                ],
                "parry": "A",
                "karaRange": 0,
                "damage": 5,
                "stun": 3,
                "meterAtkWhiff": 0,
                "meterAtkHit": 2,
                "meterAtkBlk": 1,
                "meterOppHit": 0,
                "meterOppBlk": 0,
                "moveMotion": "N",
                "moveButton": "LP",
                "image": "https://srk.shib.live/images/3/3a/%28makotolp%29.gif"
            },
            "Stand MP": {
                "moveName": "Stand MP",
                "plnCmd": "MP",
                "numCmd": "5MP",
                "startup": 8,
                "active": 11,
                "recovery": 4,
                "onBlock": 6,
                "onHit": 7,
                "onHitCrouch": 8,
                "moveType": "normal",
                "cancelsTo": [
                    "sp",
                    "su"
                ],
                "parry": "H",
                "karaRange": 0,
                "damage": 14,
                "stun": 9,
                "meterAtkWhiff": 2,
                "meterAtkHit": 11,
                "meterAtkBlk": 6,
                "meterOppHit": 2,
                "meterOppBlk": 0,
                "moveMotion": "N",
                "moveButton": "MP",
                "image": "https://srk.shib.live/images/7/7a/%28makotomp%29.gif"
            },
            "Stand HP": {
                "moveName": "Stand HP",
                "plnCmd": "HP",
                "numCmd": "5HP",
                "startup": 8,
                "active": 2,
                "recovery": 22,
                "onBlock": -5,
                "onHit": -3,
                "onHitCrouch": -1,
                "moveType": "normal",
                "cancelsTo": [
                    "sp",
                    "su"
                ],
                "parry": "H",
                "karaRange": 0,
                "damage": 21,
                "stun": 15,
                "meterAtkWhiff": 3,
                "meterAtkHit": 19,
                "meterAtkBlk": 10,
                "meterOppHit": 4,
                "meterOppBlk": 0,
                "moveMotion": "N",
                "moveButton": "HP",
                "image": "https://srk.shib.live/images/6/6a/%28makotohp%29.gif"
            },
            "Stand LK": {
                "moveName": "Stand LK",
                "plnCmd": "LK",
                "numCmd": "5LK",
                "startup": 4,
                "active": 5,
                "recovery": 12,
                "onBlock": -2,
                "onHit": -2,
                "onHitCrouch": -2,
                "moveType": "normal",
                "cancelsTo": [
                    "sp",
                    "su"
                ],
                "parry": "A",
                "karaRange": 7,
                "damage": 7,
                "stun": 3,
                "meterAtkWhiff": 0,
                "meterAtkHit": 2,
                "meterAtkBlk": 1,
                "meterOppHit": 0,
                "meterOppBlk": 0,
                "moveMotion": "N",
                "moveButton": "LK",
                "image": "https://srk.shib.live/images/8/8b/%28makotolk%29.gif"
            },
            "Stand MK": {
                "moveName": "Stand MK",
                "plnCmd": "MK",
                "numCmd": "5MK",
                "startup": 7,
                "active": 5,
                "recovery": 13,
                "onBlock": -2,
                "onHit": -1,
                "onHitCrouch": 0,
                "moveType": "normal",
                "parry": "A",
                "karaRange": 7,
                "damage": 16,
                "stun": 7,
                "meterAtkWhiff": 2,
                "meterAtkHit": 11,
                "meterAtkBlk": 6,
                "meterOppHit": 2,
                "meterOppBlk": 0,
                "moveMotion": "N",
                "moveButton": "MK",
                "image": "https://srk.shib.live/images/6/6c/%28makotomk%29.gif"
            },
            "Stand HK": {
                "moveName": "Stand HK",
                "plnCmd": "HK",
                "numCmd": "5HK",
                "startup": 11,
                "active": 9,
                "recovery": 13,
                "onBlock": 0,
                "onHit": 2,
                "onHitCrouch": 4,
                "moveType": "normal",
                "parry": "H",
                "karaRange": -24,
                "damage": 23,
                "stun": 7,
                "meterAtkWhiff": 3,
                "meterAtkHit": 19,
                "meterAtkBlk": 10,
                "meterOppHit": 4,
                "meterOppBlk": 0,
                "moveMotion": "N",
                "moveButton": "HK",
                "image": "https://srk.shib.live/images/8/86/%28makotohk%29.gif"
            },
            "Kazami": {
                "moveName": "Kazami",
                "cmnName": "Forward LP",
                "plnCmd": "f+LP",
                "numCmd": "6LP",
                "startup": 4,
                "active": 4,
                "recovery": 8,
                "onBlock": 0,
                "onHit": 0,
                "onHitCrouch": 0,
                "moveType": "normal",
                "cancelsTo": [
                    "self",
                    "sp",
                    "su"
                ],
                "parry": "A",
                "karaRange": 0,
                "damage": 4,
                "stun": 3,
                "meterAtkWhiff": 0,
                "meterAtkHit": 2,
                "meterAtkBlk": 1,
                "meterOppHit": 0,
                "meterOppBlk": 0,
                "moveMotion": "F",
                "moveButton": "LP",
                "image": "https://srk.shib.live/images/4/49/%28makotoflp%29.gif"
            },
            "Kaoruna": {
                "moveName": "Kaoruna",
                "cmnName": "Forward MP",
                "plnCmd": "f+MP",
                "numCmd": "6MP",
                "startup": 9,
                "active": 6,
                "recovery": 9,
                "onBlock": 2,
                "onHit": 3,
                "onHitCrouch": 4,
                "moveType": "normal",
                "parry": "H",
                "karaRange": 4,
                "damage": 15,
                "stun": 5,
                "meterAtkWhiff": 2,
                "meterAtkHit": 11,
                "meterAtkBlk": 6,
                "meterOppHit": 2,
                "meterOppBlk": 0,
                "moveMotion": "F",
                "moveButton": "MP",
                "image": "https://srk.shib.live/images/5/51/%28makotofmp%29.gif"
            },
            "Shimaki": {
                "moveName": "Shimaki",
                "cmnName": "Forward HP",
                "plnCmd": "f+HP",
                "numCmd": "6HP",
                "startup": 16,
                "active": 12,
                "recovery": 16,
                "onBlock": -4,
                "onHit": -2,
                "onHitCrouch": 0,
                "moveType": "normal",
                "parry": "H",
                "karaRange": 0,
                "damage": 26,
                "stun": 13,
                "meterAtkWhiff": 3,
                "meterAtkHit": 17,
                "meterAtkBlk": 7,
                "meterOppHit": 4,
                "meterOppBlk": 0,
                "moveMotion": "F",
                "moveButton": "HP",
                "image": "https://srk.shib.live/images/7/7c/%28makotofhp%29.gif"
            },
            "Shimaki > Yamase": {
                "moveName": "Shimaki > Yamase",
                "cmnName": "Forward HP (x3)",
                "plnCmd": "f+HP, HP, HP",
                "numCmd": "6HP, HP, HP",
                "startup": 16,
                "active": 23,
                "recovery": 13,
                "onBlock": -4,
                "onHit": -3,
                "onHitCrouch": -2,
                "moveType": "normal",
                "parry": "H",
                "karaRange": 0,
                "damage": 31,
                "stun": 17,
                "meterAtkWhiff": 3,
                "meterAtkHit": 29,
                "meterAtkBlk": 11,
                "meterOppHit": 8,
                "meterOppBlk": 0,
                "moveMotion": "N",
                "moveButton": "HP",
                "followUp": true,
                "image": "https://www.justnopoint.com/zweifuss/colorswap.php?pcolorstring=MakotoPalette.bin&pcolornum=0&pname=makoto/makoto-fhp-hold.gif"
            },
            "Shibuki": {
                "moveName": "Shibuki",
                "cmnName": "Forward LK",
                "plnCmd": "f+LK",
                "numCmd": "6LK",
                "startup": 6,
                "active": 6,
                "recovery": 13,
                "onBlock": -5,
                "onHit": -5,
                "onHitCrouch": -5,
                "moveType": "normal",
                "parry": "A",
                "karaRange": 4,
                "damage": 6,
                "stun": 5,
                "meterAtkWhiff": 0,
                "meterAtkHit": 2,
                "meterAtkBlk": 1,
                "meterOppHit": 0,
                "meterOppBlk": 0,
                "moveMotion": "F",
                "moveButton": "LK",
                "image": "https://srk.shib.live/images/0/07/%28makotoflk%29.gif"
            },
            "Naruto": {
                "moveName": "Naruto",
                "cmnName": "Forward MK",
                "plnCmd": "f+MK",
                "numCmd": "6MK",
                "startup": 17,
                "active": 5,
                "recovery": 18,
                "onBlock": -5,
                "onHit": -3,
                "onHitCrouch": -1,
                "moveType": "normal",
                "parry": "H",
                "karaRange": 2,
                "damage": 17,
                "stun": 9,
                "meterAtkWhiff": 2,
                "meterAtkHit": 11,
                "meterAtkBlk": 6,
                "meterOppHit": 2,
                "meterOppBlk": 0,
                "moveMotion": "F",
                "moveButton": "MK",
                "image": "https://srk.shib.live/images/b/b8/%28makotofmk%29.gif"
            },
            "Kuroshio": {
                "moveName": "Kuroshio",
                "cmnName": "Forward HK",
                "plnCmd": "f+HK",
                "numCmd": "6HK",
                "startup": 22,
                "active": 3,
                "recovery": 25,
                "onBlock": -11,
                "onHit": "D",
                "onHitCrouch": "D",
                "moveType": "normal",
                "parry": "L",
                "karaRange": 0,
                "damage": 21,
                "stun": 5,
                "meterAtkWhiff": 3,
                "meterAtkHit": 19,
                "meterAtkBlk": 10,
                "meterOppHit": 4,
                "meterOppBlk": 0,
                "moveMotion": "F",
                "moveButton": "HK",
                "image": "https://srk.shib.live/images/d/d0/%28makotofhk%29.gif"
            },
            "Kuroshio (Fake)": {
                "moveName": "Kuroshio (Fake)",
                "cmnName": "Forward HK (Fake)",
                "plnCmd": "f+HK (Hold)",
                "numCmd": "6HK (Hold)",
                "startup": 1,
                "image": "https://srk.shib.live/images/d/d0/%28makotofhk%29.gif"
            },
            "Crouch LP": {
                "moveName": "Crouch LP",
                "plnCmd": "d+LP",
                "numCmd": "2LP",
                "startup": 5,
                "active": 4,
                "recovery": 5,
                "onBlock": 3,
                "onHit": 3,
                "onHitCrouch": 3,
                "moveType": "normal",
                "cancelsTo": [
                    "self",
                    "sp",
                    "su"
                ],
                "parry": "A",
                "karaRange": 0,
                "damage": 3,
                "stun": 3,
                "meterAtkWhiff": 0,
                "meterAtkHit": 2,
                "meterAtkBlk": 1,
                "meterOppHit": 0,
                "meterOppBlk": 0,
                "moveMotion": "D",
                "moveButton": "LP",
                "image": "https://srk.shib.live/images/f/fe/%28makotoclp%29.gif"
            },
            "Crouch MP": {
                "moveName": "Crouch MP",
                "plnCmd": "d+MP",
                "numCmd": "2MP",
                "startup": 7,
                "active": 7,
                "recovery": 11,
                "onBlock": -1,
                "onHit": 0,
                "onHitCrouch": 1,
                "moveType": "normal",
                "cancelsTo": [
                    "sp",
                    "su"
                ],
                "parry": "A",
                "karaRange": 3,
                "damage": 12,
                "stun": 5,
                "meterAtkWhiff": 2,
                "meterAtkHit": 11,
                "meterAtkBlk": 6,
                "meterOppHit": 2,
                "meterOppBlk": 0,
                "moveMotion": "D",
                "moveButton": "MP",
                "image": "https://srk.shib.live/images/d/de/%28makotocmp%29.gif"
            },
            "Crouch HP": {
                "moveName": "Crouch HP",
                "plnCmd": "d+HP",
                "numCmd": "2HP",
                "startup": 10,
                "active": 2,
                "recovery": 21,
                "onBlock": -6,
                "onHit": "D",
                "onHitCrouch": "D",
                "moveType": "normal",
                "parry": "L",
                "karaRange": 0,
                "damage": 17,
                "stun": 3,
                "meterAtkWhiff": 3,
                "meterAtkHit": 19,
                "meterAtkBlk": 10,
                "meterOppHit": 4,
                "meterOppBlk": 0,
                "moveMotion": "D",
                "moveButton": "HP",
                "image": "https://srk.shib.live/images/7/74/%28makotochp%29.gif"
            },
            "Crouch LK": {
                "moveName": "Crouch LK",
                "plnCmd": "d+LK",
                "numCmd": "2LK",
                "startup": 4,
                "active": 6,
                "recovery": 10,
                "onBlock": -3,
                "onHit": -3,
                "onHitCrouch": -3,
                "moveType": "normal",
                "cancelsTo": [
                    "sp",
                    "su"
                ],
                "parry": "L",
                "karaRange": 0,
                "damage": 5,
                "stun": 3,
                "meterAtkWhiff": 0,
                "meterAtkHit": 2,
                "meterAtkBlk": 1,
                "meterOppHit": 0,
                "meterOppBlk": 0,
                "moveMotion": "D",
                "moveButton": "LK",
                "image": "https://srk.shib.live/images/6/61/%28makotoclk%29.gif"
            },
            "Crouch MK": {
                "moveName": "Crouch MK",
                "plnCmd": "d+MK",
                "numCmd": "2MK",
                "startup": 7,
                "active": 8,
                "recovery": 7,
                "onBlock": 3,
                "onHit": 4,
                "onHitCrouch": 5,
                "moveType": "normal",
                "parry": "A",
                "karaRange": 0,
                "damage": 16,
                "stun": 5,
                "meterAtkWhiff": 2,
                "meterAtkHit": 11,
                "meterAtkBlk": 6,
                "meterOppHit": 2,
                "meterOppBlk": 0,
                "moveMotion": "D",
                "moveButton": "MK",
                "image": "https://srk.shib.live/images/9/9a/%28makotocmk%29.gif"
            },
            "Crouch HK": {
                "moveName": "Crouch HK",
                "plnCmd": "d+HK",
                "numCmd": "2HK",
                "startup": 10,
                "active": 4,
                "recovery": 12,
                "onBlock": 2,
                "onHit": 4,
                "onHitCrouch": 6,
                "moveType": "normal",
                "parry": "H",
                "karaRange": 13,
                "damage": 23,
                "stun": 15,
                "meterAtkWhiff": 3,
                "meterAtkHit": 19,
                "meterAtkBlk": 10,
                "meterOppHit": 4,
                "meterOppBlk": 0,
                "moveMotion": "D",
                "moveButton": "HK",
                "image": "https://srk.shib.live/images/a/a1/%28makotochk%29.gif"
            },
            "Jump LP (Neutral)": {
                "moveName": "Jump LP (Neutral)",
                "plnCmd": "u+LP",
                "numCmd": "8LP",
                "startup": 9,
                "active": 17,
                "moveType": "normal",
                "parry": "H",
                "karaRange": 0,
                "damage": 8,
                "stun": 7,
                "meterAtkWhiff": 0,
                "meterAtkHit": 2,
                "meterAtkBlk": 1,
                "meterOppHit": 0,
                "meterOppBlk": 0,
                "moveMotion": "U",
                "moveButton": "LP",
                "airmove": true,
                "image": "https://srk.shib.live/images/b/bd/%28makotonjlp%29.gif"
            },
            "Jump LP": {
                "moveName": "Jump LP",
                "plnCmd": "j+LP",
                "numCmd": "j.LP",
                "startup": 4,
                "active": 21,
                "moveType": "normal",
                "parry": "H",
                "karaRange": 0,
                "damage": 8,
                "stun": 7,
                "meterAtkWhiff": 0,
                "meterAtkHit": 2,
                "meterAtkBlk": 1,
                "meterOppHit": 0,
                "meterOppBlk": 0,
                "moveMotion": "U",
                "moveButton": "LP",
                "airmove": true,
                "image": "https://srk.shib.live/images/8/8d/%28makotojlp%29.gif"
            },
            "Jump MP (Neutral)": {
                "moveName": "Jump MP (Neutral)",
                "plnCmd": "u+MP",
                "numCmd": "8MP",
                "startup": 11,
                "active": 10,
                "moveType": "normal",
                "parry": "H",
                "karaRange": 0,
                "damage": 14,
                "stun": 11,
                "meterAtkWhiff": 2,
                "meterAtkHit": 11,
                "meterAtkBlk": 6,
                "meterOppHit": 2,
                "meterOppBlk": 0,
                "moveMotion": "U",
                "moveButton": "MP",
                "airmove": true,
                "image": "https://srk.shib.live/images/9/9c/%28makotojnmp%29.gif"
            },
            "Jump MP": {
                "moveName": "Jump MP",
                "plnCmd": "j+MP",
                "numCmd": "j.MP",
                "startup": 11,
                "active": 23,
                "moveType": "normal",
                "parry": "H",
                "karaRange": 0,
                "damage": 12,
                "stun": 11,
                "meterAtkWhiff": 2,
                "meterAtkHit": 11,
                "meterAtkBlk": 6,
                "meterOppHit": 2,
                "meterOppBlk": 0,
                "moveMotion": "U",
                "moveButton": "MP",
                "airmove": true,
                "image": "https://srk.shib.live/images/e/e8/%28makotojmp%29.gif"
            },
            "Jump HP (Neutral)": {
                "moveName": "Jump HP (Neutral)",
                "plnCmd": "u+HP",
                "numCmd": "8HP",
                "startup": 13,
                "active": 2,
                "moveType": "normal",
                "parry": "H",
                "karaRange": 0,
                "damage": 23,
                "stun": 15,
                "meterAtkWhiff": 3,
                "meterAtkHit": 19,
                "meterAtkBlk": 10,
                "meterOppHit": 4,
                "meterOppBlk": 0,
                "moveMotion": "U",
                "moveButton": "HP",
                "airmove": true,
                "image": "https://srk.shib.live/images/a/a6/%28makotonjhp%29.gif"
            },
            "Jump HP": {
                "moveName": "Jump HP",
                "plnCmd": "j+HP",
                "numCmd": "j.HP",
                "startup": 10,
                "active": 2,
                "moveType": "normal",
                "parry": "H",
                "karaRange": 0,
                "damage": 26,
                "stun": 15,
                "meterAtkWhiff": 3,
                "meterAtkHit": 19,
                "meterAtkBlk": 10,
                "meterOppHit": 4,
                "meterOppBlk": 0,
                "moveMotion": "U",
                "moveButton": "HP",
                "airmove": true,
                "image": "https://srk.shib.live/images/6/63/%28makotojhp%29.gif"
            },
            "Jump LK": {
                "moveName": "Jump LK",
                "plnCmd": "j+LK",
                "numCmd": "j.LK",
                "startup": 2,
                "active": 14,
                "moveType": "normal",
                "parry": "H",
                "karaRange": 0,
                "damage": 10,
                "stun": 7,
                "meterAtkWhiff": 0,
                "meterAtkHit": 2,
                "meterAtkBlk": 1,
                "meterOppHit": 0,
                "meterOppBlk": 0,
                "moveMotion": "U",
                "moveButton": "LK",
                "airmove": true,
                "image": "https://srk.shib.live/images/f/f7/%28makotojlk%29.gif"
            },
            "Jump MK": {
                "moveName": "Jump MK",
                "plnCmd": "j+MK",
                "numCmd": "j.MK",
                "startup": 7,
                "active": 13,
                "moveType": "normal",
                "parry": "H",
                "karaRange": 0,
                "damage": 16,
                "stun": 9,
                "meterAtkWhiff": 2,
                "meterAtkHit": 11,
                "meterAtkBlk": 6,
                "meterOppHit": 2,
                "meterOppBlk": 0,
                "moveMotion": "U",
                "moveButton": "MK",
                "airmove": true,
                "image": "https://srk.shib.live/images/6/66/%28makotojmk%29.gif"
            },
            "Jump HK": {
                "moveName": "Jump HK",
                "plnCmd": "j+HK",
                "numCmd": "j.HK",
                "startup": 6,
                "active": 6,
                "moveType": "normal",
                "parry": "H",
                "karaRange": 0,
                "damage": 23,
                "stun": 11,
                "meterAtkWhiff": 3,
                "meterAtkHit": 19,
                "meterAtkBlk": 10,
                "meterOppHit": 4,
                "meterOppBlk": 0,
                "moveMotion": "U",
                "moveButton": "HK",
                "airmove": true,
                "image": "https://srk.shib.live/images/5/5b/%28makotojhk%29.gif"
            },
            "Tacchuu": {
                "moveName": "Tacchuu",
                "cmnName": "Neutral Throw",
                "plnCmd": "LP+LK",
                "numCmd": "LPLK",
                "startup": 2,
                "active": 1,
                "recovery": 21,
                "onBlock": 0,
                "onHit": "D",
                "onHitCrouch": "D",
                "moveType": "throw",
                "karaRange": 0,
                "throwRange": 20,
                "damage": 16,
                "stun": 16,
                "meterAtkWhiff": 0,
                "meterAtkHit": 8,
                "meterAtkBlk": 0,
                "meterOppHit": 2,
                "meterOppBlk": 7,
                "moveMotion": "N",
                "moveButton": "LPLK",
                "image": "https://srk.shib.live/images/3/35/%28makotothr%29.gif"
            },
            "Araiso": {
                "moveName": "Araiso",
                "cmnName": "Back/Fwd Throw",
                "plnCmd": "b/f+LP+LK",
                "numCmd": "4/6LPLK",
                "startup": 2,
                "active": 1,
                "recovery": 21,
                "onBlock": 0,
                "onHit": "D",
                "onHitCrouch": "D",
                "moveType": "throw",
                "karaRange": 0,
                "throwRange": 20,
                "damage": 21,
                "stun": 10,
                "meterAtkWhiff": 0,
                "meterAtkHit": 7,
                "meterAtkBlk": 0,
                "meterOppHit": 2,
                "meterOppBlk": 7,
                "moveMotion": "BorF",
                "moveButton": "LPLK",
                "image": "https://srk.shib.live/images/7/78/%28makotobftr%29.gif"
            },
            "Chigusa": {
                "moveName": "Chigusa",
                "cmnName": "Universal Overhead",
                "plnCmd": "MP+MK",
                "numCmd": "MPMK",
                "startup": 15,
                "active": 10,
                "recovery": 5,
                "moveType": "throw",
                "parry": "H",
                "karaRange": 0,
                "damage": 7,
                "stun": 3,
                "meterAtkWhiff": 0,
                "meterAtkHit": 2,
                "meterAtkBlk": 1,
                "meterOppHit": 0,
                "meterOppBlk": 0,
                "moveMotion": "N",
                "moveButton": "MPMK",
                "image": "https://srk.shib.live/images/c/c2/%28makotooh%29.gif"
            },
            "Kiai wo Reru": {
                "moveName": "Kiai wo Reru",
                "cmnName": "Taunt",
                "plnCmd": "HP+HK",
                "numCmd": "HPHK",
                "startup": 79,
                "active": 3,
                "moveType": "taunt",
                "cancelsTo": [
                    "su"
                ],
                "parry": "A",
                "karaRange": 13,
                "damage": 1,
                "stun": 3,
                "meterAtkWhiff": 18,
                "meterAtkHit": 20,
                "meterAtkBlk": 19,
                "meterOppHit": 0,
                "meterOppBlk": 0,
                "moveMotion": "N",
                "moveButton": "HPHK",
                "image": "https://srk.shib.live/images/1/13/%28makotot%29.gif"
            },
            "LP Hayate": {
                "moveName": "LP Hayate",
                "cmnName": "LP Dash Punch",
                "plnCmd": "qcf+LP",
                "numCmd": "236LP",
                "startup": 6,
                "active": 6,
                "recovery": 24,
                "onBlock": -12,
                "onHit": 2,
                "onHitCrouch": 4,
                "moveType": "special",
                "parry": "H",
                "damage": 17,
                "stun": 9,
                "meterAtkWhiff": 3,
                "meterAtkHit": 15,
                "meterAtkBlk": 7,
                "meterOppHit": 3,
                "meterOppBlk": 0,
                "moveMotion": "QCF",
                "moveButton": "LP",
                "image": "https://srk.shib.live/images/1/10/%28makotohayate%29.gif"
            },
            "MP Hayate": {
                "moveName": "MP Hayate",
                "cmnName": "MP Dash Punch",
                "plnCmd": "qcf+MP",
                "numCmd": "236MP",
                "startup": 9,
                "active": 6,
                "recovery": 24,
                "onBlock": -12,
                "onHit": 2,
                "onHitCrouch": 4,
                "moveType": "special",
                "parry": "H",
                "damage": 17,
                "stun": 9,
                "meterAtkWhiff": 3,
                "meterAtkHit": 15,
                "meterAtkBlk": 7,
                "meterOppHit": 3,
                "meterOppBlk": 0,
                "moveMotion": "QCF",
                "moveButton": "MP",
                "image": "https://srk.shib.live/images/1/10/%28makotohayate%29.gif"
            },
            "HP Hayate": {
                "moveName": "HP Hayate",
                "cmnName": "HP Dash Punch",
                "plnCmd": "qcf+HP",
                "numCmd": "236HP",
                "startup": 11,
                "active": 6,
                "recovery": 24,
                "onBlock": -12,
                "onHit": 2,
                "onHitCrouch": 4,
                "moveType": "special",
                "parry": "H",
                "damage": 17,
                "stun": 9,
                "meterAtkWhiff": 3,
                "meterAtkHit": 15,
                "meterAtkBlk": 7,
                "meterOppHit": 3,
                "meterOppBlk": 0,
                "moveMotion": "QCF",
                "moveButton": "HP",
                "image": "https://srk.shib.live/images/1/10/%28makotohayate%29.gif"
            },
            "EX Hayate": {
                "moveName": "EX Hayate",
                "cmnName": "EX Dash Punch",
                "plnCmd": "qcf+PP",
                "numCmd": "236PP",
                "startup": 17,
                "active": 6,
                "recovery": 24,
                "onBlock": 2,
                "onHit": "D",
                "onHitCrouch": "D",
                "moveType": "special",
                "parry": "H",
                "damage": 28,
                "stun": 17,
                "meterAtkWhiff": -40,
                "meterAtkHit": -40,
                "meterAtkBlk": -40,
                "meterOppHit": 0,
                "meterOppBlk": 0,
                "moveMotion": "QCF",
                "moveButton": "2P",
                "image": "https://srk.shib.live/images/f/f2/%28makotohdkex%29.gif"
            },
            "Hayate (Lv 1)": {
                "moveName": "Hayate (Lv 1)",
                "cmnName": "Dash Punch (Lv 1)",
                "plnCmd": "qcf+P (7F hold)",
                "numCmd": "236P (7F hold)",
                "startup": 7,
                "active": 6,
                "recovery": 24,
                "onBlock": -9,
                "onHit": 2,
                "onHitCrouch": 4,
                "moveType": "special",
                "parry": "H",
                "damage": 19,
                "stun": 11,
                "meterAtkWhiff": 3,
                "meterAtkHit": 15,
                "meterAtkBlk": 7,
                "meterOppHit": 3,
                "meterOppBlk": 0,
                "moveMotion": "QCF",
                "moveButton": "1P",
                "image": "https://srk.shib.live/images/1/10/%28makotohayate%29.gif"
            },
            "Hayate (Lv 2)": {
                "moveName": "Hayate (Lv 2)",
                "cmnName": "Dash Punch (Lv 2)",
                "plnCmd": "qcf+P (27F hold)",
                "numCmd": "236P (27F hold)",
                "startup": 27,
                "active": 6,
                "recovery": 24,
                "onBlock": -6,
                "onHit": 2,
                "onHitCrouch": 4,
                "moveType": "special",
                "parry": "H",
                "damage": 21,
                "stun": 13,
                "meterAtkWhiff": 3,
                "meterAtkHit": 15,
                "meterAtkBlk": 7,
                "meterOppHit": 3,
                "meterOppBlk": 0,
                "moveMotion": "QCF",
                "moveButton": "1P",
                "image": "https://srk.shib.live/images/1/10/%28makotohayate%29.gif"
            },
            "Hayate (Lv 3)": {
                "moveName": "Hayate (Lv 3)",
                "cmnName": "Dash Punch (Lv 3)",
                "plnCmd": "qcf+P (47F hold)",
                "numCmd": "236P (47F hold)",
                "startup": 47,
                "active": 6,
                "recovery": 24,
                "onBlock": -2,
                "onHit": "D",
                "onHitCrouch": "D",
                "moveType": "special",
                "parry": "H",
                "damage": 24,
                "stun": 13,
                "meterAtkWhiff": 3,
                "meterAtkHit": 15,
                "meterAtkBlk": 7,
                "meterOppHit": 3,
                "meterOppBlk": 0,
                "moveMotion": "QCF",
                "moveButton": "1P",
                "image": "https://srk.shib.live/images/1/10/%28makotohayate%29.gif"
            },
            "Hayate (Lv 4)": {
                "moveName": "Hayate (Lv 4)",
                "cmnName": "Dash Punch (Lv 4)",
                "plnCmd": "qcf+P (67F hold)",
                "numCmd": "236P (67F hold)",
                "startup": "#VALUE!",
                "active": 6,
                "recovery": 24,
                "onBlock": 2,
                "onHit": "D",
                "onHitCrouch": "D",
                "moveType": "special",
                "parry": "H",
                "damage": 24,
                "stun": 17,
                "meterAtkWhiff": 3,
                "meterAtkHit": 15,
                "meterAtkBlk": 7,
                "meterOppHit": 3,
                "meterOppBlk": 0,
                "moveMotion": "QCF",
                "moveButton": "1P",
                "image": "https://srk.shib.live/images/1/10/%28makotohayate%29.gif"
            },
            "LP Fukiage": {
                "moveName": "LP Fukiage",
                "cmnName": "LP DP",
                "plnCmd": "f,d,df+LP",
                "numCmd": "623LP",
                "startup": 7,
                "active": 8,
                "recovery": 26,
                "moveType": "special",
                "cancelsTo": [
                    "su",
                    "sj"
                ],
                "parry": "A",
                "damage": 21,
                "stun": 29,
                "meterAtkWhiff": 3,
                "meterAtkHit": 21,
                "meterAtkBlk": "---",
                "meterOppHit": 6,
                "meterOppBlk": "---",
                "moveMotion": "DP",
                "moveButton": "LP",
                "antiAirMove": true,
                "image": "https://srk.shib.live/images/2/2a/%28makotofkage%29.gif"
            },
            "MP Fukiage": {
                "moveName": "MP Fukiage",
                "cmnName": "MP DP",
                "plnCmd": "f,d,df+MP",
                "numCmd": "623MP",
                "startup": 10,
                "active": 8,
                "recovery": 26,
                "moveType": "special",
                "cancelsTo": [
                    "su",
                    "sj"
                ],
                "parry": "A",
                "damage": 24,
                "stun": 31,
                "meterAtkWhiff": 3,
                "meterAtkHit": 21,
                "meterAtkBlk": "---",
                "meterOppHit": 6,
                "meterOppBlk": "---",
                "moveMotion": "DP",
                "moveButton": "MP",
                "antiAirMove": true,
                "image": "https://srk.shib.live/images/2/2a/%28makotofkage%29.gif"
            },
            "HP Fukiage": {
                "moveName": "HP Fukiage",
                "cmnName": "HP DP",
                "plnCmd": "f,d,df+HP",
                "numCmd": "623HP",
                "startup": 14,
                "active": 8,
                "recovery": 26,
                "moveType": "special",
                "cancelsTo": [
                    "su",
                    "sj"
                ],
                "parry": "A",
                "damage": 28,
                "stun": 31,
                "meterAtkWhiff": 3,
                "meterAtkHit": 21,
                "meterAtkBlk": "---",
                "meterOppHit": 6,
                "meterOppBlk": "---",
                "moveMotion": "DP",
                "moveButton": "HP",
                "antiAirMove": true,
                "image": "https://srk.shib.live/images/2/2a/%28makotofkage%29.gif"
            },
            "EX Fukiage": {
                "moveName": "EX Fukiage",
                "cmnName": "EX DP",
                "plnCmd": "f,d,df+PP",
                "numCmd": "623PP",
                "startup": 11,
                "active": 8,
                "recovery": 26,
                "moveType": "special",
                "cancelsTo": [
                    "su",
                    "sj"
                ],
                "parry": "A",
                "damage": 24,
                "stun": 21,
                "meterAtkWhiff": -40,
                "meterAtkHit": -40,
                "meterAtkBlk": "---",
                "meterOppHit": 0,
                "meterOppBlk": "---",
                "moveMotion": "DP",
                "moveButton": "2P",
                "antiAirMove": true,
                "image": "https://srk.shib.live/images/5/53/%28makotosrkex%29.gif"
            },
            "LP Oroshi": {
                "moveName": "LP Oroshi",
                "cmnName": "LP Chop",
                "plnCmd": "qcb+LP",
                "numCmd": "214LP",
                "startup": 19,
                "active": 7,
                "recovery": 17,
                "onBlock": -4,
                "moveType": "special",
                "cancelsTo": [
                    "su"
                ],
                "parry": "H",
                "damage": 17,
                "stun": 7,
                "meterAtkWhiff": 3,
                "meterAtkHit": 18,
                "meterAtkBlk": 12,
                "meterOppHit": 4,
                "meterOppBlk": 0,
                "moveMotion": "QCB",
                "moveButton": "LP",
                "image": "https://srk.shib.live/images/6/6e/%28makotooroshi%29.gif"
            },
            "MP Oroshi": {
                "moveName": "MP Oroshi",
                "cmnName": "MP Chop",
                "plnCmd": "qcb+MP",
                "numCmd": "214MP",
                "startup": 23,
                "active": 7,
                "recovery": 17,
                "onBlock": -4,
                "moveType": "special",
                "cancelsTo": [
                    "su"
                ],
                "parry": "H",
                "damage": 19,
                "stun": 11,
                "meterAtkWhiff": 3,
                "meterAtkHit": 18,
                "meterAtkBlk": 12,
                "meterOppHit": 4,
                "meterOppBlk": 0,
                "moveMotion": "QCB",
                "moveButton": "MP",
                "image": "https://srk.shib.live/images/6/6e/%28makotooroshi%29.gif"
            },
            "HP Oroshi": {
                "moveName": "HP Oroshi",
                "cmnName": "HP Chop",
                "plnCmd": "qcb+HP",
                "numCmd": "214HP",
                "startup": 28,
                "active": 7,
                "recovery": 17,
                "onBlock": 0,
                "moveType": "special",
                "cancelsTo": [
                    "su"
                ],
                "parry": "H",
                "damage": 24,
                "stun": 13,
                "meterAtkWhiff": 3,
                "meterAtkHit": 18,
                "meterAtkBlk": 12,
                "meterOppHit": 4,
                "meterOppBlk": 0,
                "moveMotion": "QCB",
                "moveButton": "HP",
                "image": "https://srk.shib.live/images/6/6e/%28makotooroshi%29.gif"
            },
            "EX Oroshi": {
                "moveName": "EX Oroshi",
                "cmnName": "EX Chop",
                "plnCmd": "qcb+PP",
                "numCmd": "214PP",
                "startup": 13,
                "active": 7,
                "recovery": 17,
                "onBlock": 4,
                "moveType": "special",
                "cancelsTo": [
                    "su"
                ],
                "parry": "H",
                "damage": 28,
                "stun": 9,
                "meterAtkWhiff": -40,
                "meterAtkHit": -40,
                "meterAtkBlk": -40,
                "meterOppHit": 0,
                "meterOppBlk": 0,
                "moveMotion": "QCB",
                "moveButton": "2P",
                "image": "https://srk.shib.live/images/f/fa/%28makototskex%29.gif"
            },
            "LK Tsurugi": {
                "moveName": "LK Tsurugi",
                "cmnName": "LK Axe Kick",
                "plnCmd": "qcb+LK (air)",
                "numCmd": "214LK (air)",
                "startup": 14,
                "active": 4,
                "onBlock": 1,
                "moveType": "special",
                "parry": "H",
                "damage": 24,
                "stun": 13,
                "meterAtkWhiff": 3,
                "meterAtkHit": 19,
                "meterAtkBlk": 12,
                "meterOppHit": 4,
                "meterOppBlk": 0,
                "moveMotion": "QCB",
                "moveButton": "LK",
                "airmove": true,
                "image": "https://srk.shib.live/images/9/96/%28makotoatsur%29.gif"
            },
            "MK Tsurugi": {
                "moveName": "MK Tsurugi",
                "cmnName": "MK Axe Kick",
                "plnCmd": "qcb+MK (air)",
                "numCmd": "214MK (air)",
                "startup": 15,
                "active": 4,
                "onBlock": 1,
                "moveType": "special",
                "parry": "H",
                "damage": 26,
                "stun": 13,
                "meterAtkWhiff": 3,
                "meterAtkHit": 19,
                "meterAtkBlk": 12,
                "meterOppHit": 4,
                "meterOppBlk": 0,
                "moveMotion": "QCB",
                "moveButton": "MK",
                "airmove": true,
                "image": "https://srk.shib.live/images/9/96/%28makotoatsur%29.gif"
            },
            "HK Tsurugi": {
                "moveName": "HK Tsurugi",
                "cmnName": "HK Axe Kick",
                "plnCmd": "qcb+HK (air)",
                "numCmd": "214HK (air)",
                "startup": 16,
                "active": 4,
                "onBlock": 1,
                "moveType": "special",
                "parry": "H",
                "damage": 28,
                "stun": 13,
                "meterAtkWhiff": 3,
                "meterAtkHit": 19,
                "meterAtkBlk": 12,
                "meterOppHit": 4,
                "meterOppBlk": 0,
                "moveMotion": "QCB",
                "moveButton": "HK",
                "airmove": true,
                "image": "https://srk.shib.live/images/9/96/%28makotoatsur%29.gif"
            },
            "EX Tsurugi": {
                "moveName": "EX Tsurugi",
                "cmnName": "EX Axe Kick",
                "plnCmd": "qcb+KK (air)",
                "numCmd": "214KK (air)",
                "startup": 15,
                "active": 4,
                "onBlock": 3,
                "moveType": "special",
                "parry": "H",
                "damage": 17,
                "stun": 9,
                "meterAtkWhiff": -40,
                "meterAtkHit": -40,
                "meterAtkBlk": -40,
                "meterOppHit": 0,
                "meterOppBlk": 0,
                "moveMotion": "QCB",
                "moveButton": "2K",
                "airmove": true,
                "image": "https://srk.shib.live/images/6/64/%28makotoatskex%29.gif"
            },
            "LK Karakusa": {
                "moveName": "LK Karakusa",
                "cmnName": "LK Command Grab",
                "plnCmd": "hcb+LK",
                "numCmd": "63214LK",
                "startup": 7,
                "active": 3,
                "recovery": 28,
                "moveType": "command-grab",
                "throwRange": 53,
                "damage": 5,
                "stun": 8,
                "meterAtkWhiff": 0,
                "meterAtkHit": 8,
                "meterAtkBlk": "---",
                "meterOppHit": 2,
                "meterOppBlk": "---",
                "moveMotion": "HCB",
                "moveButton": "LK",
                "image": "https://srk.shib.live/images/c/c0/%28makotokarakusa%29.gif"
            },
            "MK Karakusa": {
                "moveName": "MK Karakusa",
                "cmnName": "MK Command Grab",
                "plnCmd": "hcb+MK",
                "numCmd": "63214MK",
                "startup": 8,
                "active": 4,
                "recovery": 29,
                "moveType": "command-grab",
                "throwRange": 57,
                "damage": 5,
                "stun": 8,
                "meterAtkWhiff": 0,
                "meterAtkHit": 8,
                "meterAtkBlk": "---",
                "meterOppHit": 2,
                "meterOppBlk": "---",
                "moveMotion": "HCB",
                "moveButton": "MK",
                "image": "https://srk.shib.live/images/c/c0/%28makotokarakusa%29.gif"
            },
            "HK Karakusa": {
                "moveName": "HK Karakusa",
                "cmnName": "HK Command Grab",
                "plnCmd": "hcb+HK",
                "numCmd": "63214HK",
                "startup": 9,
                "active": 4,
                "recovery": 30,
                "moveType": "command-grab",
                "throwRange": 61,
                "damage": 5,
                "stun": 8,
                "meterAtkWhiff": 0,
                "meterAtkHit": 8,
                "meterAtkBlk": "---",
                "meterOppHit": 2,
                "meterOppBlk": "---",
                "moveMotion": "HCB",
                "moveButton": "HK",
                "image": "https://srk.shib.live/images/c/c0/%28makotokarakusa%29.gif"
            },
            "Seichuusen Godanzuki": {
                "moveName": "Seichuusen Godanzuki",
                "cmnName": "SA1",
                "plnCmd": "qcf,qcf+P (SA1)",
                "numCmd": "236236P (SA1)",
                "startup": 1,
                "active": 3,
                "recovery": 65,
                "onBlock": -17,
                "moveType": "super",
                "parry": "A",
                "damage": 83,
                "stun": 20,
                "moveMotion": "DQCF",
                "moveButton": "1P",
                "image": "https://srk.shib.live/images/5/50/%28makotosa1%29.gif"
            },
            "Abare Tosanami": {
                "moveName": "Abare Tosanami",
                "cmnName": "SA2",
                "plnCmd": "qcf,qcf+K (SA2)",
                "numCmd": "236236K (SA2)",
                "startup": "#VALUE!",
                "active": 5,
                "recovery": 25,
                "onBlock": -20,
                "moveType": "super",
                "cancelsTo": [
                    "dash",
                    "sj"
                ],
                "parry": "H",
                "damage": 59,
                "stun": 22,
                "moveMotion": "DQCF",
                "moveButton": "1K",
                "image": "https://srk.shib.live/images/3/3c/%28makotosa2%29.gif"
            },
            "Tanden Renki": {
                "moveName": "Tanden Renki",
                "cmnName": "SA3",
                "plnCmd": "qcf,qcf+P (SA3)",
                "numCmd": "236236P (SA3)",
                "moveType": "super",
                "moveMotion": "DQCF",
                "moveButton": "1P",
                "image": "https://srk.shib.live/images/7/7e/%28makotosa3%29.gif"
            },
            "input": "None"
        }
    },
    "stats": {
        "health": 1200,
        "stun": 64,
        "SA1 (stock/size)": "1/120",
        "SA2 (stock/size)": "2/88",
        "SA3 (stock/size)": "1/96",
        "nJump": "41(4+34+3)",
        "fJump": "41(4+34+3)",
        "bJump": "42(4+35+3)",
        "nSuperJump": "46(6+37+3)",
        "fSuperJump": "45(6+36+3)",
        "bSuperJump": "45(6+36+3)",
        "fDash": 12,
        "bDash": 15,
        "color": "#f1c40f",
        "phrase": "It hurts twice as much when you know that it was your fault!",
        "wakeupNormal": 71,
        "wakeupQuick": 43,
        "threeLetterCode": "mak",
        "image": "https://srk.shib.live/images/9/92/Makoto3s-stance.gif"
    }
}